{
  "objects": [
    {
      "name": "Floor",
      "position": [
        0,
        0,
        0
      ],
      "rotation": [
        0,
        0,
        0
      ],
      "scale": [
        1,
        1,
        1
      ],
      "components": [
        {
          "type": "ModelRenderer",
          "mesh": "plane",
          "meshSize": [
            60,
            60
          ],
          "color": "LightGray"
        },
        {
          "type": "BoxCollider",
          "size": [
            60,
            1,
            60
          ],
          "offset": [
            0,
            -0.5,
            0
          ]
        }
      ]
    },
    {
      "name": "Cube_0",
      "position": [
        12.945765,
        3,
        -8.329315
      ],
      "rotation": [
        25,
        15,
        30
      ],
      "scale": [
        1,
        1,
        1
      ],
      "components": [
        {
          "type": "ModelRenderer",
          "mesh": "cube",
          "meshSize": [
            1.5,
            1.5,
            1.5
          ],
          "color": "Red"
        },
        {
          "type": "BoxCollider",
          "size": [
            1.5,
            1.5,
            1.5
          ],
          "offset": [
            0,
            0,
            0
          ]
        },
        {
          "type": "Rigidbody",
          "mass": 1,
          "bounciness": 0.6,
          "friction": 0.08,
          "useGravity": true
        }
      ],
      "children": [
        {
          "name": "Antenna",
          "position": [0, 1.5, 0],
          "rotation": [0, 0, 0],
          "scale": [0.3, 0.3, 0.3],
          "components": [
            {
              "type": "ModelRenderer",
              "mesh": "cube",
              "meshSize": [1, 1, 1],
              "color": "Gold"
            }
          ]
        }
      ]
    },
    {
      "name": "Cube_1",
      "position": [
        12.532137,
        4,
        9.938409
      ],
      "rotation": [
        45,
        10,
        -20
      ],
      "scale": [
        1,
        1,
        1
      ],
      "components": [
        {
          "type": "ModelRenderer",
          "mesh": "cube",
          "meshSize": [
            1.5,
            1.5,
            1.5
          ],
          "color": "Blue"
        },
        {
          "type": "BoxCollider",
          "size": [
            1.5,
            1.5,
            1.5
          ],
          "offset": [
            0,
            0,
            0
          ]
        },
        {
          "type": "Rigidbody",
          "mass": 1,
          "bounciness": 0.5,
          "friction": 0.1,
          "useGravity": true
        }
      ]
    },
    {
      "name": "Cube_2",
      "position": [
        0,
        3.5,
        19.28185
      ],
      "rotation": [
        -15,
        35,
        12
      ],
      "scale": [
        1,
        1,
        1
      ],
      "components": [
        {
          "type": "ModelRenderer",
          "mesh": "cube",
          "meshSize": [
            1.5,
            1.5,
            1.5
          ],
          "color": "Green"
        },
        {
          "type": "BoxCollider",
          "size": [
            1.5,
            1.5,
            1.5
          ],
          "offset": [
            0,
            0,
            0
          ]
        },
        {
          "type": "Rigidbody",
          "mass": 1,
          "bounciness": 0.7,
          "friction": 0.06,
          "useGravity": true
        }
      ]
    },
    {
      "name": "Cube_3",
      "position": [
        -13.349342,
        0.75,
        5.5
      ],
      "rotation": [
        0,
        0,
        0
      ],
      "scale": [
        1,
        1,
        1
      ],
      "components": [
        {
          "type": "ModelRenderer",
          "mesh": "cube",
          "meshSize": [
            1.5,
            1.5,
            1.5
          ],
          "color": "Purple"
        },
        {
          "type": "BoxCollider",
          "size": [
            1.5,
            1.5,
            1.5
          ],
          "offset": [
            0,
            0,
            0
          ]
        },
        {
          "type": "Rigidbody",
          "mass": 1,
          "bounciness": 0.4,
          "friction": 0.12,
          "useGravity": true
        }
      ]
    },
    {
      "name": "Cube_4",
      "position": [
        -8,
        0.75,
        17.137682
      ],
      "rotation": [
        0,
        0,
        0
      ],
      "scale": [
        1,
        1,
        1
      ],
      "components": [
        {
          "type": "ModelRenderer",
          "mesh": "cube",
          "meshSize": [
            1.5,
            1.5,
            1.5
          ],
          "color": "Orange"
        },
        {
          "type": "BoxCollider",
          "size": [
            1.5,
            1.5,
            1.5
          ],
          "offset": [
            0,
            0,
            0
          ]
        },
        {
          "type": "Rigidbody",
          "mass": 1,
          "bounciness": 0.55,
          "friction": 0.09,
          "useGravity": true
        }
      ]
    },
    {
      "name": "Cube_5",
      "position": [
        -5.5,
        0.75,
        -16.479649
      ],
      "rotation": [
        0,
        0,
        0
      ],
      "scale": [
        1,
        1,
        1
      ],
      "components": [
        {
          "type": "ModelRenderer",
          "mesh": "cube",
          "meshSize": [
            1.5,
            1.5,
            1.5
          ],
          "color": "Yellow"
        },
        {
          "type": "BoxCollider",
          "size": [
            1.5,
            1.5,
            1.5
          ],
          "offset": [
            0,
            0,
            0
          ]
        },
        {
          "type": "Rigidbody",
          "mass": 1,
          "bounciness": 0.65,
          "friction": 0.07,
          "useGravity": true
        }
      ]
    },
    {
      "name": "Cube_6",
      "position": [
        0,
        0.75,
        -8
      ],
      "rotation": [
        0,
        0,
        0
      ],
      "scale": [
        1,
        1,
        1
      ],
      "components": [
        {
          "type": "ModelRenderer",
          "mesh": "cube",
          "meshSize": [
            1.5,
            1.5,
            1.5
          ],
          "color": "Pink"
        },
        {
          "type": "BoxCollider",
          "size": [
            1.5,
            1.5,
            1.5
          ],
          "offset": [
            0,
            0,
            0
          ]
        },
        {
          "type": "Rigidbody",
          "mass": 1,
          "bounciness": 0.45,
          "friction": 0.11,
          "useGravity": true
        }
      ]
    },
    {
      "name": "Cube_7",
      "position": [
        5.5,
        0.75,
        -5.5
      ],
      "rotation": [
        0,
        0,
        0
      ],
      "scale": [
        1,
        1,
        1
      ],
      "components": [
        {
          "type": "ModelRenderer",
          "mesh": "cube",
          "meshSize": [
            1.5,
            1.5,
            1.5
          ],
          "color": "SkyBlue"
        },
        {
          "type": "BoxCollider",
          "size": [
            1.5,
            1.5,
            1.5
          ],
          "offset": [
            0,
            0,
            0
          ]
        },
        {
          "type": "Rigidbody",
          "mass": 1,
          "bounciness": 0.5,
          "friction": 0.1,
          "useGravity": true
        }
      ]
    },
    {
      "name": "Cube_8",
      "position": [
        18.482151,
        0.75,
        -3.6390104
      ],
      "rotation": [
        0,
        0,
        0
      ],
      "scale": [
        1,
        1,
        1
      ],
      "components": [
        {
          "type": "ModelRenderer",
          "mesh": "cube",
          "meshSize": [
            1.5,
            1.5,
            1.5
          ],
          "color": "Lime"
        },
        {
          "type": "BoxCollider",
          "size": [
            1.5,
            1.5,
            1.5
          ],
          "offset": [
            0,
            0,
            0
          ]
        },
        {
          "type": "Rigidbody",
          "mass": 1,
          "bounciness": 0.6,
          "friction": 0.08,
          "useGravity": true
        }
      ]
    },
    {
      "name": "Cube_9",
      "position": [
        -10.437426,
        0.75,
        -6.1397104
      ],
      "rotation": [
        0,
        0,
        0
      ],
      "scale": [
        1,
        1,
        1
      ],
      "components": [
        {
          "type": "ModelRenderer",
          "mesh": "cube",
          "meshSize": [
            1.5,
            1.5,
            1.5
          ],
          "color": "Magenta"
        },
        {
          "type": "BoxCollider",
          "size": [
            1.5,
            1.5,
            1.5
          ],
          "offset": [
            0,
            0,
            0
          ]
        },
        {
          "type": "Rigidbody",
          "mass": 1,
          "bounciness": 0.5,
          "friction": 0.1,
          "useGravity": true
        }
      ]
    },
    {
      "name": "Duck",
      "position": [
        0,
        0.3,
        0
      ],
      "rotation": [
        0,
        107.58131,
        0
      ],
      "scale": [
        10,
        10,
        10
      ],
      "components": [
        {
          "type": "ModelRenderer",
          "model": "assets/models/rubber_duck_toy_1k.gltf/rubber_duck_toy_1k.gltf",
          "color": "White"
        },
        {
          "type": "Script",
          "name": "Rotator",
          "props": {
            "speed": 45
          }
        },
        {
          "type": "BoxCollider",
          "size": [
            0.8,
            0.6,
            0.8
          ],
          "offset": [
            0,
            0,
            0
          ]
        },
        {
          "type": "Rigidbody",
          "mass": 1,
          "bounciness": 0.6,
          "friction": 0.1,
          "useGravity": true
        }
      ]
    },
    {
      "name": "DirectionalLight",
      "position": [
        0,
        0,
        0
      ],
      "rotation": [
        0,
        0,
        0
      ],
      "scale": [
        1,
        1,
        1
      ],
      "components": [
        {
          "type": "DirectionalLight",
          "direction": [
            0.31367752,
            -0.89622146,
            -0.31367752
          ],
          "intensity": 1
        }
      ]
    }
  ]
}